pygorpho/__init__.py
pygorpho/_thin.py
pygorpho/constants.py
pygorpho/cuda.py
pygorpho/flat.py
pygorpho/gen.py
pygorpho/pygorpho.dll
pygorpho/strel.py
pygorpho-1.0.1.dist-info/LICENSE.txt
pygorpho-1.0.1.dist-info/METADATA
pygorpho-1.0.1.dist-info/WHEEL
pygorpho-1.0.1.dist-info/top_level.txt
pygorpho-1.0.1.dist-info/RECORD
