Metadata-Version: 2.1
Name: pygorpho
Version: 1.0.1
Summary: Python bindings for gorpho
Home-page: https://pygorpho.readthedocs.io/
Author: Patrick M. Jensen
Author-email: patmjen@gmail.com
License: MIT
Project-URL: Documentation, https://pygorpho.readthedocs.io/en/latest/api-doc.html
Project-URL: PyPI, https://pypi.org/project/pygorpho/
Project-URL: Source, https://github.com/patmjen/pygorpho
Platform: UNKNOWN
Requires-Dist: numpy
Requires-Dist: scikit-build (>=0.7.0)
